isjsonvalid/__init__.py
isjsonvalid/helpers.py
isjsonvalid/validation.py
isjsonvalid-1.0.0.dist-info/METADATA
isjsonvalid-1.0.0.dist-info/WHEEL
isjsonvalid-1.0.0.dist-info/top_level.txt
isjsonvalid-1.0.0.dist-info/RECORD
